.DS_Store
propensityscore/__init__.py
propensityscore/core.py
propensityscore-1.0.1.dist-info/LICENSE
propensityscore-1.0.1.dist-info/METADATA
propensityscore-1.0.1.dist-info/WHEEL
propensityscore-1.0.1.dist-info/top_level.txt
propensityscore-1.0.1.dist-info/RECORD
