Metadata-Version: 2.1
Name: propensityscore
Version: 1.0.1
Summary: Program to Calculate Optimal Propensity Score
Home-page: https://github.com/lucashusted/propensityscore
Author: Lucas Husted
Author-email: lucas.f.husted@columbia.edu
License: MIT
Platform: UNKNOWN
Classifier: Development Status :: 3 - Alpha
Classifier: Intended Audience :: End Users/Desktop
Classifier: Intended Audience :: Financial and Insurance Industry
Classifier: Intended Audience :: Science/Research
Classifier: Programming Language :: Python :: 3.6
Classifier: Programming Language :: Python :: 3.7
Classifier: Programming Language :: Python :: 3.8
Classifier: Operating System :: MacOS :: MacOS X
Classifier: Operating System :: Microsoft :: Windows
Classifier: Operating System :: POSIX
Classifier: Programming Language :: Python
Requires-Python: >=3
Requires-Dist: statsmodels
Requires-Dist: pandas
Requires-Dist: scipy
Requires-Dist: numpy
Requires-Dist: joblib
Requires-Dist: scikit-learn
